fgen_example-0.3.0.dist-info/METADATA
fgen_example-0.3.0.dist-info/WHEEL
fgen_example-0.3.0.dist-info/entry_points.txt
fgen_example-0.3.0.dist-info/RECORD
fgen_example.libs/libgfortran-1f0d579a.so.5.0.0
fgen_example.libs/libquadmath-d6be75ba.so.0.0.0
share/licenses/test-drive/LICENSE-Apache
share/licenses/test-drive/LICENSE-MIT
include/fgen/GNU-12.2.1/fgen_timeseries.mod
include/fgen/GNU-12.2.1/fgen_char_conversions.mod
include/fgen/GNU-12.2.1/fgen_rk.mod
include/fgen/GNU-12.2.1/fgen_1d_get_boundary_value.mod
include/fgen/GNU-12.2.1/fgen_euler_forward.mod
include/fgen/GNU-12.2.1/fgen_values_bounded.mod
include/fgen/GNU-12.2.1/fgen_array_helpers.mod
include/fgen/GNU-12.2.1/fgen_1d_differentiation.mod
include/fgen/GNU-12.2.1/fgen_1d_next.mod
include/fgen/GNU-12.2.1/fgen_1d_previous.mod
include/fgen/GNU-12.2.1/fgen_1d_integration.mod
include/fgen/GNU-12.2.1/fgen_interpolation.mod
include/fgen/GNU-12.2.1/fgen_utils.mod
include/fgen/GNU-12.2.1/fgen_base_stepper.mod
include/fgen/GNU-12.2.1/fgen_solve_ivp.mod
include/fgen/GNU-12.2.1/fgen_1d_interpolation_base.mod
include/fgen/GNU-12.2.1/fgen_1d_handling_options.mod
include/fgen/GNU-12.2.1/fgen_base_finalizable.mod
include/fgen/GNU-12.2.1/fgen_time.mod
include/fgen/GNU-12.2.1/fgen_1d_linear_spline.mod
include/fgen/GNU-12.2.1/fgen_1d_interpolation.mod
include/test-drive/GNU-12.2.1/testdrive.mod
include/test-drive/GNU-12.2.1/testdrive_version.mod
lib64/libfgen.a
lib64/libtest-drive.a
lib64/cmake/fgen/fgen-targets-release.cmake
lib64/cmake/fgen/fgen-targets.cmake
lib64/cmake/test-drive/test-drive-targets-release.cmake
lib64/cmake/test-drive/test-drive-config.cmake
lib64/cmake/test-drive/test-drive-targets.cmake
lib64/cmake/test-drive/test-drive-config-version.cmake
lib64/pkgconfig/test-drive.pc
fgen_example/operations.py
fgen_example/_lib.cpython-311-x86_64-linux-gnu.so
fgen_example/__init__.py
fgen_example/py.typed
fgen_example/derived_type.py
fgen_example/_lib/operations_manager.f90
fgen_example/_lib/derived_type.f90
fgen_example/_lib/operations.f90
fgen_example/_lib/derived_type.yaml
fgen_example/_lib/operations.yaml
