Metadata-Version: 2.1
Name: fgen-example
Version: 0.3.0
Summary: Example project using fgen to wrap a simple module
Author: Jared Lewis, email = jared.lewis@climate-resource.com
Requires-Python: >=3.10
Requires-Dist: pint>=0.22
Requires-Dist: numpy>=0.22
Requires-Dist: fgen==0.4.1
